kofi/__init__.py
kofi/_version.py
kofi/core.py
kofi/grapefruit.py
kofi-0.0.1.dist-info/LICENSE.txt
kofi-0.0.1.dist-info/METADATA
kofi-0.0.1.dist-info/WHEEL
kofi-0.0.1.dist-info/namespace_packages.txt
kofi-0.0.1.dist-info/top_level.txt
kofi-0.0.1.dist-info/RECORD
