Metadata-Version: 2.1
Name: kofi
Version: 0.0.1
Summary: Color scales and color conversion made easy for Python.
Home-page: http://github.com/Sweelol/spectra
Author: Francis Selorm Kponyo
Author-email: pojoba01@gmail.com
License: MIT
Keywords: color colors colorspace scale spectrum
Platform: UNKNOWN
Classifier: Development Status :: 3 - Alpha
Classifier: Intended Audience :: Developers
Classifier: License :: OSI Approved :: MIT License
Classifier: Operating System :: OS Independent
Classifier: Programming Language :: Python :: 3.5
Classifier: Programming Language :: Python :: 3.6
Classifier: Programming Language :: Python :: 3.7
Classifier: Programming Language :: Python :: 3.8
Classifier: Programming Language :: Python :: 3.9
Classifier: Programming Language :: Python :: 3.10
Classifier: Programming Language :: Python :: 3.11
Classifier: Topic :: Education
Requires-Dist: colormath (>=3.0.0)
